pyltover/__init__.py
pyltover/base.py
pyltover/client.py
pyltover/schema.py
pyltover/servers.py
pyltover/apis/__init__.py
pyltover/apis/errors.py
pyltover/apis/schema.py
pyltover/apis/v1/__init__.py
pyltover/apis/v1/schema.py
pyltover/apis/v1/urls.py
pyltover/apis/v2/__init__.py
pyltover/apis/v3/__init__.py
pyltover/apis/v3/schema.py
pyltover/apis/v3/urls.py
pyltover/apis/v4/__init__.py
pyltover/apis/v4/schema.py
pyltover/apis/v4/urls.py
pyltover/apis/v5/__init__.py
pyltover/apis/v5/schema.py
pyltover/apis/v5/urls.py
pyltover-0.1.8.dist-info/METADATA
pyltover-0.1.8.dist-info/WHEEL
pyltover-0.1.8.dist-info/RECORD
