Metadata-Version: 2.3
Name: pyltover
Version: 0.1.8
Summary: Python wrapper around riot games developer api.
Author-email: Sepehr Hamzehlouy <s.hamzelooy@gmail.com>
Requires-Python: >=3.11
Requires-Dist: httpx>=0.28.1
Requires-Dist: orjson>=3.10.18
Requires-Dist: pydantic>=2.11.7
